README.md
setup.py
cpp_build/sample.exe
half_sample.egg-info/PKG-INFO
half_sample.egg-info/SOURCES.txt
half_sample.egg-info/dependency_links.txt
half_sample.egg-info/top_level.txt
sample/__init__.py
sample/process.py
sample/result.py
sample/sample.py