Metadata-Version: 2.1
Name: half-sample
Version: 0.1.12
Summary: sample data and analysis
Home-page: https://github.com/KD-Group/Half.Sample
Author: kunde
Author-email: gzkunde@163.com
License: UNKNOWN
Platform: UNKNOWN
Classifier: Programming Language :: Python :: 3
Classifier: License :: OSI Approved :: MIT License
Classifier: Operating System :: OS Independent
